vdam_data_crawler/__init__.py
vdam_data_crawler/main.py
vdam_data_crawler-0.1.0.dist-info/METADATA
vdam_data_crawler-0.1.0.dist-info/WHEEL
vdam_data_crawler-0.1.0.dist-info/RECORD
